odxtools/__init__.py
odxtools/__main__.py
odxtools/additionalaudience.py
odxtools/addrdeffilter.py
odxtools/addrdefphyssegment.py
odxtools/addressing.py
odxtools/admindata.py
odxtools/audience.py
odxtools/basecomparam.py
odxtools/basefunctionnode.py
odxtools/basevariantpattern.py
odxtools/basicstructure.py
odxtools/checksum.py
odxtools/checksumresult.py
odxtools/codec.py
odxtools/commrelation.py
odxtools/commrelationvaluetype.py
odxtools/companydata.py
odxtools/companydocinfo.py
odxtools/companyrevisioninfo.py
odxtools/companyspecificinfo.py
odxtools/comparam.py
odxtools/comparaminstance.py
odxtools/comparamspec.py
odxtools/comparamsubset.py
odxtools/complexcomparam.py
odxtools/complexdop.py
odxtools/componentconnector.py
odxtools/compositecodec.py
odxtools/configdata.py
odxtools/configdatadictionaryspec.py
odxtools/configiditem.py
odxtools/configitem.py
odxtools/configrecord.py
odxtools/createanycomparam.py
odxtools/createanydiagcodedtype.py
odxtools/database.py
odxtools/datablock.py
odxtools/datafile.py
odxtools/dataformat.py
odxtools/dataformatselection.py
odxtools/dataiditem.py
odxtools/dataobjectproperty.py
odxtools/datarecord.py
odxtools/decodestate.py
odxtools/description.py
odxtools/determinenumberofitems.py
odxtools/diagclasstype.py
odxtools/diagcodedtype.py
odxtools/diagcomm.py
odxtools/diagcommdataconnector.py
odxtools/diagdatadictionaryspec.py
odxtools/diaglayercontainer.py
odxtools/diagnostictroublecode.py
odxtools/diagobjectconnector.py
odxtools/diagservice.py
odxtools/diagvariable.py
odxtools/direction.py
odxtools/docrevision.py
odxtools/dopbase.py
odxtools/dtcconnector.py
odxtools/dtcdop.py
odxtools/dynamicendmarkerfield.py
odxtools/dynamiclengthfield.py
odxtools/dyndefinedspec.py
odxtools/dynenddopref.py
odxtools/dyniddefmodeinfo.py
odxtools/ecuconfig.py
odxtools/ecugroup.py
odxtools/ecumem.py
odxtools/ecumemconnector.py
odxtools/ecuproxy.py
odxtools/ecuvariantpattern.py
odxtools/element.py
odxtools/encodestate.py
odxtools/encoding.py
odxtools-11.0.2.dist-info/licenses/LICENSE
odxtools-11.0.2.dist-info/METADATA
odxtools-11.0.2.dist-info/WHEEL
odxtools-11.0.2.dist-info/entry_points.txt
odxtools-11.0.2.dist-info/top_level.txt
odxtools-11.0.2.dist-info/RECORD
