Metadata-Version: 2.4
Name: odxtools
Version: 11.0.2
Summary: Utilities to work with the ODX standard for automotive diagnostics
Author-email: Katrin Bauer <katrin.bauer@mbition.io>, Andreas Lauser <andreas.lauser@mbition.io>, Ayoub Kaanich <kayoub5@live.com>
Maintainer-email: Andreas Lauser <andreas.lauser@mbition.io>, Ayoub Kaanich <kayoub5@live.com>
License: MIT
Project-URL: Homepage, https://github.com/mercedes-benz/odxtools
Project-URL: Bug Tracker, https://github.com/mercedes-benz/odxtools/issues
Project-URL: Repository, https://github.com/mercedes-benz/odxtools
Keywords: can,can bus,DoIP,odx,pdx,obd,uds,automotive,diagnostics
Classifier: Programming Language :: Python :: 3
Classifier: Programming Language :: Python :: 3.10
Classifier: Programming Language :: Python :: 3.11
Classifier: Programming Language :: Python :: 3.12
Classifier: Programming Language :: Python :: 3.13
Classifier: Development Status :: 5 - Production/Stable
Classifier: Environment :: Console
Classifier: Intended Audience :: Developers
Classifier: License :: OSI Approved :: MIT License
Classifier: Operating System :: OS Independent
Requires-Python: >=3.10
License-File: LICENSE
Requires-Dist: bitstruct>=8.17
Requires-Dist: argparse_addons>=0.12
Requires-Dist: jinja2>=3.1
Requires-Dist: python-can>=4.2
Requires-Dist: markdownify>=0.11
Requires-Dist: deprecation>=2.1
Requires-Dist: packaging
Requires-Dist: rich>=13.7
Requires-Dist: typing_extensions>=4.9
Requires-Dist: bincopy>=20.1
Provides-Extra: browse-tool
Requires-Dist: InquirerPy>=0.3.4; extra == "browse-tool"
Provides-Extra: test
Requires-Dist: mypy>=1.5; extra == "test"
Requires-Dist: ruff>=0.0.290; extra == "test"
Requires-Dist: pytest>=7.4; extra == "test"
Requires-Dist: coverage>=7.3; extra == "test"
Provides-Extra: examples
Requires-Dist: can-isotp>=1.9; extra == "examples"
Provides-Extra: all
Requires-Dist: odxtools[browse-tool,examples,test]; extra == "all"
Dynamic: license-file
